envrihub/__init__.py
envrihub/dataset.py
envrihub/decorators.py
envrihub/hub.py
envrihub/cos/__init__.py
envrihub/cos/catalogue.py
envrihub/cos/models.py
envrihub/cos/utils.py
envrihub/data_access/__init__.py
envrihub/data_access/argo.py
envrihub/data_access/catalogue_metadata_client.py
envrihub/data_access/models.py
envrihub/data_access/open_api_client.py
envrihub/data_access/seadatanet.py
envrihub/data_access/utils.py
envrihub-0.0.13.dist-info/licenses/LICENSE
envrihub-0.0.13.dist-info/METADATA
envrihub-0.0.13.dist-info/WHEEL
envrihub-0.0.13.dist-info/top_level.txt
envrihub-0.0.13.dist-info/RECORD
