Metadata-Version: 2.4
Name: envrihub
Version: 0.0.13
Summary: Python library to streamline interaction with the ENVRI-Hub APIs, providing a pythonic facade to data and service access.
Home-page: https://gitlab.a.incd.pt/envri-hub-next/vre-lib
Author: ENVRI Community
Author-email: envri-hub-next-wp13-14@mailman.egi.eu
License: MIT
License-File: LICENSE
Requires-Dist: shapely
Requires-Dist: retry
Requires-Dist: openapi3-parser
Requires-Dist: prance
Requires-Dist: pandas
Requires-Dist: argopy
Requires-Dist: SPARQLWrapper
Dynamic: author
Dynamic: author-email
Dynamic: description
Dynamic: description-content-type
Dynamic: home-page
Dynamic: license
Dynamic: license-file
Dynamic: requires-dist
Dynamic: summary
